camgrab/__init__.py
camgrab/camgrab.py
camgrab-0.9.1.dist-info/DESCRIPTION.rst
camgrab-0.9.1.dist-info/METADATA
camgrab-0.9.1.dist-info/RECORD
camgrab-0.9.1.dist-info/WHEEL
camgrab-0.9.1.dist-info/metadata.json
camgrab-0.9.1.dist-info/top_level.txt
