Metadata-Version: 2.0
Name: camgrab
Version: 0.9.1
Summary: Python library for grabbing images from webcams
Home-page: https://github.com/takeontom/camgrab
Author: Tom Smith
Author-email: tom@takeontom.com
License: MIT license
Platform: UNKNOWN
Classifier: Development Status :: 2 - Pre-Alpha
Classifier: Intended Audience :: Developers
Classifier: License :: OSI Approved :: MIT License
Classifier: Natural Language :: English
Classifier: Programming Language :: Python :: 3.5
Classifier: Programming Language :: Python :: 3.6
Requires-Dist: pillow (>=4)
